diagnostics/storages.py
diagnostics/utils.py
diagnostics/_py3k.py
diagnostics/__init__.py
diagnostics/formatters/_html.py
diagnostics/formatters/__init__.py
diagnostics/logging/_formatter.py
diagnostics/logging/_handler.py
diagnostics/logging/__init__.py
diagnostics/models/code.py
diagnostics/models/environment.py
diagnostics/models/excinfo.py
diagnostics/models/frame.py
diagnostics/models/variable.py
diagnostics/models/__init__.py
diagnostics/templates/python_logo.png
diagnostics/templates/script.js
diagnostics/templates/style.css
diagnostics-0.2.4.dist-info/DESCRIPTION.rst
diagnostics-0.2.4.dist-info/METADATA
diagnostics-0.2.4.dist-info/metadata.json
diagnostics-0.2.4.dist-info/RECORD
diagnostics-0.2.4.dist-info/top_level.txt
diagnostics-0.2.4.dist-info/WHEEL
