Metadata-Version: 2.0
Name: diagnostics
Version: 0.2.4
Summary: Alternative to Python's module `cgitb` with template inspired by Nette and Django
Home-page: https://github.com/miso-belica/diagnostics
Author: Michal Belica
Author-email: miso.belica@gmail.com
License: Copyright 2013 Michal Belica
